HISTORY.rst
LICENSE
MANIFEST.in
README.rst
flask_reggie.py
setup.py
Flask_Reggie.egg-info/PKG-INFO
Flask_Reggie.egg-info/SOURCES.txt
Flask_Reggie.egg-info/dependency_links.txt
Flask_Reggie.egg-info/not-zip-safe
Flask_Reggie.egg-info/requires.txt
Flask_Reggie.egg-info/top_level.txt