Metadata-Version: 1.1
Name: Flask-Reggie
Version: 0.0.2
Summary: Flask Regex Routes.
Home-page: http://github.com/rhyselsmore/flask-reggie
Author: Rhys Elsmore
Author-email: me@rhys.io
License: Copyright 2013 Rhys Elsmore
